setup.py
rongcloud/__init__.py
rongcloud/base.py
rongcloud/chatroom.py
rongcloud/group.py
rongcloud/message.py
rongcloud/push.py
rongcloud/sms.py
rongcloud/test.py
rongcloud/user.py
rongcloud/wordfilter.py
rongcloud.egg-info/PKG-INFO
rongcloud.egg-info/SOURCES.txt
rongcloud.egg-info/dependency_links.txt
rongcloud.egg-info/requires.txt
rongcloud.egg-info/top_level.txt