Metadata-Version: 1.0
Name: rongcloud
Version: 2.0.1
Summary: Rong Cloud Server SDK in Python.
Home-page: https://github.com/rongcloud/server-sdk-python
Author: rong cloud
Author-email: support@rongcloud.cn
License: UNKNOWN
Platform: UNKNOWN
